{
  "info" : {
    "name" : "Korean OCR Data Set",
    "description" : "Korean OCR Data Set (letter handwrite)",
    "date_created" : "2021-01-22 10:43:02",
    "text" : "하"
  },
  "image" : {
    "file_name" : "02730017129.jpg",
    "width" : 110,
    "height" : 105,
    "dpi" : 300,
    "bit" : 24
  },
  "text" : {
    "type" : "letter",
    "output" : "handwrite",
    "letter" : {
      "value" : "하"
    }
  },
  "license" : {
    "output" : "handwrite",
    "font" : "",
    "font_no" : "",
    "font_license" : "",
    "font_url" : "",
    "writer_no" : "027",
    "writer_gender" : "male",
    "writer_age" : "20"
  }
}